allabolag/__init__.py
allabolag/company.py
allabolag/liquidated_companies.py
allabolag/list.py
allabolag/parsers.py
allabolag/request_client.py
allabolag/utils.py
allabolag-0.9.0.dist-info/LICENSE.txt
allabolag-0.9.0.dist-info/METADATA
allabolag-0.9.0.dist-info/WHEEL
allabolag-0.9.0.dist-info/top_level.txt
allabolag-0.9.0.dist-info/RECORD
