Metadata-Version: 2.1
Name: allabolag
Version: 0.9.0
Summary: Scrape data from allabolag.se.
Home-page: https://github.com/marple-newsrobot/allabolag
Author: Jens Finnäs, Newsworthy
Author-email: jens.finnas@gmail.com
License: MIT
Download-URL: https://github.com/marple-newsrobot/allabolag/archive/0.9.0.tar.gz
Platform: UNKNOWN
Requires-Python: >=3.8
License-File: LICENSE.txt
Requires-Dist: beautifulsoup4 (>=4.7.1)
Requires-Dist: requests (>=2.22.0)
